pipper/__init__.py
pipper/authorizer.py
pipper/bundler.py
pipper/command.py
pipper/downloader.py
pipper/environment.py
pipper/info.py
pipper/installer.py
pipper/parser.py
pipper/publisher.py
pipper/repository.py
pipper/resources/authorize_action.txt
pipper/resources/bundle_action.txt
pipper/resources/command_description.txt
pipper/resources/download_action.txt
pipper/resources/info_action.txt
pipper/resources/install_action.txt
pipper/resources/profile_flag.txt
pipper/resources/publish_action.txt
pipper/s3.py
pipper/versioning/__init__.py
pipper/versioning/definitions.py
pipper/versioning/serde.py
pipper/wrapper.py
pipper-0.10.4.dist-info/METADATA
pipper-0.10.4.dist-info/WHEEL
pipper-0.10.4.dist-info/entry_points.txt
pipper-0.10.4.dist-info/RECORD
