Metadata-Version: 2.4
Name: pipper
Version: 0.10.4
Summary: A serverless Python package manager for private packages that runs on S3.
License: MIT
Keywords: aws,python,package manager,s3,serverless
Author: Scott Ernst
Author-email: swernst@gmail.com
Requires-Python: >=3.10,<4.0.0
Classifier: Development Status :: 4 - Beta
Classifier: Environment :: Console
Classifier: Intended Audience :: Developers
Classifier: License :: OSI Approved :: MIT License
Classifier: Programming Language :: Python :: 3
Classifier: Programming Language :: Python :: 3.10
Classifier: Programming Language :: Python :: 3.11
Classifier: Programming Language :: Python :: 3.12
Classifier: Programming Language :: Python :: 3.13
Classifier: Programming Language :: Python :: 3.14
Classifier: Programming Language :: Python :: 3.8
Classifier: Programming Language :: Python :: 3.9
Classifier: Topic :: Utilities
Classifier: Typing :: Typed
Requires-Dist: boto3 (>=1.16.0)
Requires-Dist: pip
Requires-Dist: requests (>=2.24.0)
Requires-Dist: semver (>=2.13.0)
Requires-Dist: setuptools
Requires-Dist: toml
Requires-Dist: wheel
Project-URL: Documentation, https://gitlab.com/rocket-boosters/pipper
Project-URL: Homepage, https://gitlab.com/rocket-boosters/pipper
Project-URL: Repository, https://gitlab.com/rocket-boosters/pipper
